CHANGES.txt
MANIFEST.in
README.txt
setup.py
Gecko/Gecko.py
Gecko/__init__.py
Gecko/__main__.py
Gecko/simulator.py
Gecko.egg-info/PKG-INFO
Gecko.egg-info/SOURCES.txt
Gecko.egg-info/dependency_links.txt
Gecko.egg-info/entry_points.txt
Gecko.egg-info/pbr.json
Gecko.egg-info/requires.txt
Gecko.egg-info/top_level.txt
Gecko/GeckoIO/I_O.py
Gecko/GeckoIO/__init__.py
Gecko/GeckoIO/Boards/ControlAnything.py
Gecko/GeckoIO/Boards/GrovePi.py
Gecko/GeckoIO/Boards/__init__.py
Gecko/demoApp/__init__.py
Gecko/demoApp/sensors.py
Gecko/templates/sensor_template.txt
Gecko/templates/sensors_template.txt
plantMOnitor/__init__.py
plantMOnitor/sensors.py